sweetpear/__init__.py
sweetpear/computed.py
sweetpear/map.py
sweetpear/type_invariant.py
sweet_pear-1.1.0.dist-info/LICENSE
sweet_pear-1.1.0.dist-info/METADATA
sweet_pear-1.1.0.dist-info/WHEEL
sweet_pear-1.1.0.dist-info/top_level.txt
sweet_pear-1.1.0.dist-info/RECORD
