Metadata-Version: 2.1
Name: sweet-pear
Version: 1.1.0
Summary: Add basic functional methods to standard types
Home-page: https://github.com/jeremycochoy/sweet-pear
Author: Jeremy Cochoy
Author-email: jeremy.cochoy@gmail.com
License: UNKNOWN
Platform: UNKNOWN
Classifier: Programming Language :: Python :: 3
Classifier: License :: OSI Approved :: MIT License
Classifier: Operating System :: OS Independent
Requires-Dist: forbiddenfruit
Requires-Dist: cytoolz
